lex_helper/__init__.py
lex_helper/py.typed
lex_helper/channels/__init__.py
lex_helper/channels/base.py
lex_helper/channels/channel_formatting.py
lex_helper/channels/lex.py
lex_helper/channels/sms.py
lex_helper/core/__init__.py
lex_helper/core/bedrock_model_configs.py
lex_helper/core/call_handler_for_file.py
lex_helper/core/call_method_for_file.py
lex_helper/core/construct_headers.py
lex_helper/core/dialog.py
lex_helper/core/handler.py
lex_helper/core/intent_name.py
lex_helper/core/invoke_bedrock.py
lex_helper/core/logging_utils.py
lex_helper/core/make_request.py
lex_helper/core/message_manager.py
lex_helper/core/session.py
lex_helper/core/types.py
lex_helper/core/disambiguation/__init__.py
lex_helper/core/disambiguation/analyzer.py
lex_helper/core/disambiguation/bedrock_generator.py
lex_helper/core/disambiguation/handler.py
lex_helper/core/disambiguation/types.py
lex_helper/exceptions/__init__.py
lex_helper/exceptions/handlers.py
lex_helper/formatters/__init__.py
lex_helper/formatters/button.py
lex_helper/formatters/buttons.py
lex_helper/formatters/format_buttons.py
lex_helper/formatters/is_valid_url.py
lex_helper/formatters/remove_html_tags.py
lex_helper/formatters/replace_special_characters.py
lex_helper/formatters/string_to_http_url.py
lex_helper/formatters/substitute_keys_in_text.py
lex_helper/formatters/text.py
lex_helper/formatters/url.py
lex_helper/utils/__init__.py
lex_helper/utils/add_to_list.py
lex_helper/utils/common_steps_for_secret_retrieval.py
lex_helper/utils/extended_enum.py
lex_helper/utils/find_digit.py
lex_helper/utils/is_value_set.py
lex_helper/utils/split_full_name_to_first_name_and_last_name.py
lex_helper/utils/string.py
lex_helper/utils/title_to_snake.py
lex_helper/utils/type_conversion.py
lex_helper/utils/validation.py
lex_helper-0.0.3.dist-info/METADATA
lex_helper-0.0.3.dist-info/WHEEL
lex_helper-0.0.3.dist-info/licenses/LICENSE
lex_helper-0.0.3.dist-info/licenses/NOTICE
lex_helper-0.0.3.dist-info/RECORD
