Metadata-Version: 2.4
Name: lex-helper
Version: 0.0.3
Summary: A helper library for building Amazon Lex chatbots
Project-URL: Homepage, https://github.com/aws/lex-helper
Project-URL: Documentation, https://github.com/aws/lex-helper#readme
Project-URL: Issues, https://github.com/aws/lex-helper/issues
Project-URL: Repository, https://github.com/aws/lex-helper
Project-URL: Changelog, https://github.com/aws/lex-helper/blob/main/CHANGELOG.md
Project-URL: Bug Reports, https://github.com/aws/lex-helper/issues
Project-URL: Source Code, https://github.com/aws/lex-helper
Author: Amazon Web Services
License: Apache-2.0
License-File: LICENSE
License-File: NOTICE
Keywords: amazon-lex,aws,chatbot,conversational-ai,lambda,nlp,serverless,voice-assistant
Classifier: Development Status :: 4 - Beta
Classifier: Intended Audience :: Developers
Classifier: License :: OSI Approved :: Apache Software License
Classifier: Operating System :: OS Independent
Classifier: Programming Language :: Python :: 3
Classifier: Programming Language :: Python :: 3.12
Classifier: Programming Language :: Python :: 3.13
Classifier: Topic :: Communications :: Chat
Classifier: Topic :: Internet :: WWW/HTTP :: Dynamic Content
Classifier: Topic :: Scientific/Engineering :: Artificial Intelligence
Classifier: Topic :: Software Development :: Libraries :: Python Modules
Classifier: Typing :: Typed
Requires-Python: >=3.12
Requires-Dist: boto3>=1.26.0
Requires-Dist: botocore>=1.29.0
Requires-Dist: pydantic<3.0.0,>2.0.0
Requires-Dist: pyyaml<7.0,>=6.0
Provides-Extra: bedrock
Requires-Dist: aws-lambda-powertools>=3.19.0; extra == 'bedrock'
Provides-Extra: dev
Requires-Dist: aws-lambda-powertools>=3.19.0; extra == 'dev'
Requires-Dist: fuzzywuzzy>=0.18.0; extra == 'dev'
Requires-Dist: packaging>=21.0; extra == 'dev'
Requires-Dist: pre-commit>=3.0.0; extra == 'dev'
Requires-Dist: pytest-cov>=6.2.1; extra == 'dev'
Requires-Dist: pytest>=7.0.0; extra == 'dev'
Requires-Dist: python-levenshtein>=0.27.1; extra == 'dev'
Requires-Dist: ruff>=0.12.11; extra == 'dev'
